esphome_glyphsets/__init__.py
esphome_glyphsets/main.py
esphome_glyphsets/py.typed
esphome_glyphsets-0.0.1.dist-info/LICENSE
esphome_glyphsets-0.0.1.dist-info/METADATA
esphome_glyphsets-0.0.1.dist-info/WHEEL
esphome_glyphsets-0.0.1.dist-info/top_level.txt
esphome_glyphsets-0.0.1.dist-info/RECORD
