Metadata-Version: 2.2
Name: esphome-glyphsets
Version: 0.0.1
Summary: A lightweight version of glyphsets for ESPHome
Author-email: ESPHome authors <hello@openhomefoundation.org>
License: Apache Software License 2.0
Project-URL: Bug Tracker, https://github.com/esphome/esphome-glyphsets/issues
Project-URL: Changelog, https://github.com/esphome/esphome-glyphsets/blob/main/CHANGELOG.md
Project-URL: repository, https://github.com/esphome/esphome-glyphsets
Classifier: Development Status :: 2 - Pre-Alpha
Classifier: Intended Audience :: Developers
Classifier: Natural Language :: English
Classifier: Operating System :: OS Independent
Classifier: Programming Language :: Python :: 3.9
Classifier: Programming Language :: Python :: 3.10
Classifier: Programming Language :: Python :: 3.11
Classifier: Programming Language :: Python :: 3.12
Classifier: Programming Language :: Python :: 3.13
Classifier: Topic :: Software Development :: Libraries
Requires-Python: >=3.9
License-File: LICENSE
